stellarphot/__init__.py
stellarphot/_version.py
stellarphot/conftest.py
stellarphot/core.py
stellarphot/table_representations.py
stellarphot/version.py
stellarphot/data/README.rst
stellarphot/data/star_spinner.svg
stellarphot/differential_photometry/__init__.py
stellarphot/differential_photometry/aij_rel_fluxes.py
stellarphot/differential_photometry/vsx_mags.py
stellarphot/differential_photometry/tests/__init__.py
stellarphot/differential_photometry/tests/test_aij_rel_fluxes.py
stellarphot/differential_photometry/tests/test_vsx_mags.py
stellarphot/differential_photometry/tests/data/2014-12-29-ey-uma-9.fits
stellarphot/differential_photometry/tests/data/comp_stars.fits
stellarphot/differential_photometry/tests/data/variables.fits
stellarphot/gui_tools/__init__.py
stellarphot/gui_tools/comparison_functions.py
stellarphot/gui_tools/photometry_widget_functions.py
stellarphot/gui_tools/profile_and_comps.py
stellarphot/gui_tools/seeing_profile_functions.py
stellarphot/gui_tools/tests/__init__.py
stellarphot/gui_tools/tests/test_comparison_functions.py
stellarphot/gui_tools/tests/test_profile_and_comps.py
stellarphot/gui_tools/tests/test_seeing_profile.py
stellarphot/io/__init__.py
stellarphot/io/aavso_submission_schema.yml
stellarphot/io/aij.py
stellarphot/io/tess.py
stellarphot/io/tests/__init__.py
stellarphot/io/tests/test_aij_io.py
stellarphot/io/tests/test_tess.py
stellarphot/io/tests/data/aij-sample-apertures.aperture
stellarphot/io/tests/data/apertures_as_table.csv
stellarphot/notebooks/01-initial-settings.ipynb
stellarphot/notebooks/02-seeing-and-comparison.ipynb
stellarphot/notebooks/03-final-review-of-settings.ipynb
stellarphot/notebooks/04-launch-photometry.ipynb
stellarphot/notebooks/__init__.py
stellarphot/notebooks/photometry_runner.ipynb
stellarphot/notebooks/relative-flux-calculation.ipynb
stellarphot/notebooks/saveable-settings.ipynb
stellarphot/notebooks/tess-EXOTIC-fit.ipynb
stellarphot/notebooks/tess-initial-model-fit.ipynb
stellarphot-2.0.2.dist-info/METADATA
stellarphot-2.0.2.dist-info/WHEEL
stellarphot-2.0.2.dist-info/licenses/LICENSE.rst
stellarphot-2.0.2.dist-info/RECORD
