Metadata-Version: 2.4
Name: stellarphot
Version: 2.0.2
Summary: A package for performing stellar photometry.
Project-URL: Homepage, https://github.com/stellarphot/stellarphot
Author-email: Matt Craig <mattwcraig@gmail.com>
License: BSD-3-Clause
License-File: LICENSE.rst
Requires-Python: >=3.11
Requires-Dist: astropy>=5
Requires-Dist: astroquery
Requires-Dist: astrowidgets<0.4.0
Requires-Dist: bottleneck
Requires-Dist: ccdproc
Requires-Dist: ginga
Requires-Dist: ipyautoui>=0.7.19
Requires-Dist: ipyfilechooser
Requires-Dist: ipywidgets
Requires-Dist: jupyter-app-launcher>=0.3.0
Requires-Dist: lightkurve
Requires-Dist: matplotlib
Requires-Dist: pandas
Requires-Dist: papermill
Requires-Dist: photutils<3,>=2
Requires-Dist: platformdirs
Requires-Dist: pydantic>=2
Requires-Dist: pyyaml
Requires-Dist: regions
Provides-Extra: docs
Requires-Dist: graphviz; extra == 'docs'
Requires-Dist: sphinx; extra == 'docs'
Requires-Dist: sphinx-astropy[confv2]; extra == 'docs'
Requires-Dist: sphinx-design; extra == 'docs'
Provides-Extra: exo-fitting
Requires-Dist: batman-package; extra == 'exo-fitting'
Provides-Extra: test
Requires-Dist: black; extra == 'test'
Requires-Dist: pre-commit; extra == 'test'
Requires-Dist: pytest-astropy; extra == 'test'
Requires-Dist: ruff; extra == 'test'
Requires-Dist: tox; extra == 'test'
